ip_stack_api-1.0.0.dist-info/licenses/LICENSE
ipstackapi/__init__.py
ipstackapi/api_helper.py
ipstackapi/configuration.py
ipstackapi/ipstackapi_client.py
ipstackapi/controllers/__init__.py
ipstackapi/controllers/base_controller.py
ipstackapi/controllers/bulk_ip_lookup_controller.py
ipstackapi/controllers/requester_ip_lookup_controller.py
ipstackapi/controllers/standard_ip_lookup_controller.py
ipstackapi/exceptions/__init__.py
ipstackapi/exceptions/api_exception.py
ipstackapi/exceptions/error_exception.py
ipstackapi/http/__init__.py
ipstackapi/http/http_call_back.py
ipstackapi/http/http_method_enum.py
ipstackapi/http/http_request.py
ipstackapi/http/http_response.py
ipstackapi/http/auth/__init__.py
ipstackapi/http/auth/custom_query_authentication.py
ipstackapi/models/__init__.py
ipstackapi/models/connection.py
ipstackapi/models/currency.py
ipstackapi/models/error_1.py
ipstackapi/models/hostname_enum.py
ipstackapi/models/ip_location.py
ipstackapi/models/language.py
ipstackapi/models/language_1_enum.py
ipstackapi/models/location.py
ipstackapi/models/output_enum.py
ipstackapi/models/time_zone.py
ipstackapi/utilities/__init__.py
ipstackapi/utilities/file_wrapper.py
ip_stack_api-1.0.0.dist-info/METADATA
ip_stack_api-1.0.0.dist-info/WHEEL
ip_stack_api-1.0.0.dist-info/top_level.txt
ip_stack_api-1.0.0.dist-info/RECORD
